client/__init__.py
client/add_contact.py
client/client.py
client/client_database.py
client/constants.py
client/del_contact.py
client/errors.py
client/main_window.py
client/main_window_conv.py
client/metaclasses.py
client/start_dialog.py
client/transport.py
client/utils.py
client/logs/__init__.py
client/logs/config_client_log.py
client/logs/config_server_log.py
client/logs/decos.py
client/sphinx/__init__.py
client/sphinx/source/__init__.py
client/sphinx/source/conf.py
message_app_client-0.0.2.data/scripts/client_run
message_app_client-0.0.2.dist-info/METADATA
message_app_client-0.0.2.dist-info/WHEEL
message_app_client-0.0.2.dist-info/top_level.txt
message_app_client-0.0.2.dist-info/RECORD
